fast_json_repair-0.2.0.dist-info/METADATA
fast_json_repair-0.2.0.dist-info/WHEEL
fast_json_repair-0.2.0.dist-info/licenses/LICENSE
fast_json_repair/__init__.py
fast_json_repair/_fast_json_repair.abi3.so
fast_json_repair-0.2.0.dist-info/RECORD
