Metadata-Version: 2.4
Name: fast_json_repair
Version: 0.2.0
Classifier: Development Status :: 4 - Beta
Classifier: Intended Audience :: Developers
Classifier: License :: OSI Approved :: MIT License
Classifier: Programming Language :: Rust
Classifier: Programming Language :: Python :: Implementation :: CPython
Classifier: Programming Language :: Python :: 3.11
Classifier: Programming Language :: Python :: 3.12
Classifier: Programming Language :: Python :: 3.13
Classifier: Programming Language :: Python :: 3.14
Classifier: Topic :: Software Development :: Libraries :: Python Modules
Classifier: Topic :: Text Processing :: General
Classifier: Operating System :: OS Independent
Requires-Dist: orjson>=3.10.0
License-File: LICENSE
Summary: High-performance JSON repair library using Rust
Keywords: json,repair,parser,rust,performance,llm,ai
Author-email: dvideby0 <>
License: MIT
Requires-Python: >=3.11, <3.15
Project-URL: Homepage, https://github.com/dvideby0/fast_json_repair
Project-URL: Documentation, https://github.com/dvideby0/fast_json_repair#readme
Project-URL: Repository, https://github.com/dvideby0/fast_json_repair
Project-URL: Issues, https://github.com/dvideby0/fast_json_repair/issues
